README.md
setup.cfg
setup.py
ecoVI/BaseMatrix.py
ecoVI/VulnerabilityIndex.py
ecoVI/__init__.py
ecoVI.egg-info/PKG-INFO
ecoVI.egg-info/SOURCES.txt
ecoVI.egg-info/dependency_links.txt
ecoVI.egg-info/not-zip-safe
ecoVI.egg-info/top_level.txt