Metadata-Version: 1.0
Name: ecoVI
Version: 0.1
Summary: Econometric Indices
Home-page: https://github.com/satyajitovelil/eco_VI
Author: Satyajit Ovelil
Author-email: satyajitovelil@gmail.com
License: UNKNOWN
Platform: UNKNOWN
